llama_index/py.typed
llama_index/vector_stores/s3/__init__.py
llama_index/vector_stores/s3/base.py
llama_index_vector_stores_s3-0.2.1.dist-info/METADATA
llama_index_vector_stores_s3-0.2.1.dist-info/WHEEL
llama_index_vector_stores_s3-0.2.1.dist-info/licenses/LICENSE
llama_index_vector_stores_s3-0.2.1.dist-info/RECORD
