Metadata-Version: 2.4
Name: llama-index-vector-stores-s3
Version: 0.2.1
Summary: llama-index vector_stores s3Vectors integration
Author-email: Logan Markewich <logan@runllama.ai>
License-Expression: MIT
License-File: LICENSE
Requires-Python: <3.14,>=3.9
Requires-Dist: boto3>=1.39.8
Requires-Dist: llama-index-core<0.15,>=0.13.0
